source_flexport/__init__.py
source_flexport/manifest.yaml
source_flexport/run.py
source_flexport/schemas/companies.json
source_flexport/schemas/invoices.json
source_flexport/schemas/locations.json
source_flexport/schemas/products.json
source_flexport/schemas/shared/address.json
source_flexport/schemas/shared/air/shipment.json
source_flexport/schemas/shared/api/refs/collection.json
source_flexport/schemas/shared/api/refs/object.json
source_flexport/schemas/shared/company_entity/vat_number.json
source_flexport/schemas/shared/company_entity.json
source_flexport/schemas/shared/credit_memo.json
source_flexport/schemas/shared/hs_code.json
source_flexport/schemas/shared/invoice/quantity.json
source_flexport/schemas/shared/invoice/rate.json
source_flexport/schemas/shared/invoice.json
source_flexport/schemas/shared/invoice_item.json
source_flexport/schemas/shared/money.json
source_flexport/schemas/shared/network/company.json
source_flexport/schemas/shared/network/location.json
source_flexport/schemas/shared/ocean/shipment.json
source_flexport/schemas/shared/product/classification.json
source_flexport/schemas/shared/product/property.json
source_flexport/schemas/shared/product/supplier.json
source_flexport/schemas/shared/product.json
source_flexport/schemas/shared/quantity/volume.json
source_flexport/schemas/shared/quantity/weight.json
source_flexport/schemas/shared/shipment/dangerous_goods.json
source_flexport/schemas/shared/shipment.json
source_flexport/schemas/shared/shipment_item.json
source_flexport/schemas/shipments.json
source_flexport/source.py
airbyte_source_flexport-0.2.20.dist-info/METADATA
airbyte_source_flexport-0.2.20.dist-info/WHEEL
airbyte_source_flexport-0.2.20.dist-info/entry_points.txt
airbyte_source_flexport-0.2.20.dist-info/RECORD
